README.txt
setup.cfg
setup.py
Products/__init__.py
Products.AnalyticsReporting.egg-info/PKG-INFO
Products.AnalyticsReporting.egg-info/SOURCES.txt
Products.AnalyticsReporting.egg-info/dependency_links.txt
Products.AnalyticsReporting.egg-info/entry_points.txt
Products.AnalyticsReporting.egg-info/namespace_packages.txt
Products.AnalyticsReporting.egg-info/not-zip-safe
Products.AnalyticsReporting.egg-info/requires.txt
Products.AnalyticsReporting.egg-info/top_level.txt
Products/AnalyticsReporting/AnalyticsReporting.py
Products/AnalyticsReporting/__init__.py
Products/AnalyticsReporting/icon.gif
Products/AnalyticsReporting/pyGAPI.py
Products/AnalyticsReporting/version.txt
Products/AnalyticsReporting/zpt/addForm.pt
Products/AnalyticsReporting/zpt/analytics_macro.pt
Products/AnalyticsReporting/zpt/analytics_view.pt
Products/AnalyticsReporting/zpt/editForm.pt
docs/HISTORY.txt