Metadata-Version: 1.0
Name: Products.AnalyticsReporting
Version: 2.0dev-r13909
Summary: UNKNOWN
Home-page: http://www.teamrubber.com
Author: Jess Norwood
Author-email: jess.norwood@teamrubber.com
License: GPL
Platform: UNKNOWN
Classifier: Programming Language :: Python
Classifier: Topic :: Software Development :: Libraries :: Python Modules
